setup.py
basefs/__init__.py
basefs/commands.py
basefs/config.py
basefs/exceptions.py
basefs/fs.py
basefs/gossip.py
basefs/handlers.py
basefs/keys.py
basefs/logs.py
basefs/loop.py
basefs/state.py
basefs/sync.py
basefs/utils.py
basefs/validators.py
basefs/views.py
basefs.egg-info/PKG-INFO
basefs.egg-info/SOURCES.txt
basefs.egg-info/dependency_links.txt
basefs.egg-info/requires.txt
basefs.egg-info/top_level.txt
basefs/bin/basefs
basefs/management/__init__.py
basefs/management/bootstrap.py
basefs/management/get.py
basefs/management/mount.py
basefs/management/resources.py
basefs/management/run.py
basefs/management/utils.py