Metadata-Version: 1.1
Name: basefs
Version: 0.7
Summary: Basically Available, Soft state, Eventually consistent File System
Home-page: http://github.com/glic3rinu/basefs
Author: Marc Aymerich
Author-email: glicerinu@gmail.com
License: UNKNOWN
Download-URL: http://github.com/glic3rinu/basefs/tarball/master#egg=basefs
Keywords: filesystem,decentralized,distributed
Platform: UNKNOWN
Classifier: Development Status :: 4 - Beta
Classifier: Intended Audience :: Developers
Classifier: Intended Audience :: System Administrators
Classifier: Intended Audience :: Science/Research
Classifier: License :: OSI Approved :: MIT License
Classifier: Operating System :: POSIX :: Linux
Classifier: Programming Language :: Python :: 3.4
Classifier: Programming Language :: Python :: 3.5
Classifier: Programming Language :: Python :: 3 :: Only
Classifier: Topic :: System :: Networking
Classifier: Topic :: System :: Filesystems
Classifier: Topic :: System :: Distributed Computing
